uint16_to_img/convert_uint16.py
uint16_to_img-1.1.0.dist-info/LICENSE
uint16_to_img-1.1.0.dist-info/WHEEL
uint16_to_img-1.1.0.dist-info/METADATA
uint16_to_img-1.1.0.dist-info/RECORD
