Metadata-Version: 2.1
Name: uint16-to-img
Version: 1.1.0
Summary: Converts .uint16 filetypes to images
Home-page: https://github.com/jdkern11/uint16_to_img.git
Author: Joseph Kern
Author-email: jkern34@gatech.edu
Requires-Python: >=3.7,<4.0
Classifier: Programming Language :: Python :: 3
Classifier: Programming Language :: Python :: 3.7
Classifier: Programming Language :: Python :: 3.8
Classifier: Programming Language :: Python :: 3.9
Requires-Dist: numpy (>=1.2.4,<2.0.0)
Requires-Dist: opencv_python (>=4.5.2.54,<5.0.0.0)
Project-URL: Repository, https://github.com/jdkern11/uint16_to_img.git
